django_admin_2fa-1.0.0.dist-info/licenses/LICENSE
djangoadmin2fa/__init__.py
djangoadmin2fa/admin.py
djangoadmin2fa/apps.py
djangoadmin2fa/forms.py
djangoadmin2fa/middleware.py
djangoadmin2fa/models.py
djangoadmin2fa/urls.py
djangoadmin2fa/utils.py
djangoadmin2fa/views.py
djangoadmin2fa/migrations/0001_initial.py
djangoadmin2fa/migrations/0002_alter_backupcode_device_alter_trusteddevice_device.py
djangoadmin2fa/migrations/__init__.py
djangoadmin2fa/templates/admin_2fa_plus/backup_codes.html
djangoadmin2fa/templates/admin_2fa_plus/delete_device.html
djangoadmin2fa/templates/admin_2fa_plus/recovery.html
djangoadmin2fa/templates/admin_2fa_plus/setup.html
djangoadmin2fa/templates/admin_2fa_plus/verify.html
djangoadmin2fa/templates/admin_2fa_plus/verify_setup.html
django_admin_2fa-1.0.0.dist-info/METADATA
django_admin_2fa-1.0.0.dist-info/WHEEL
django_admin_2fa-1.0.0.dist-info/top_level.txt
django_admin_2fa-1.0.0.dist-info/RECORD
