Metadata-Version: 2.4
Name: django-admin-2fa
Version: 1.0.0
Summary: Two-Factor Authentication for Django Admin with TOTP, backup codes, and trusted devices.
Home-page: https://github.com/swe-himelrana/django-admin-2fa
Author: HIMEL
Author-email: python.package@himosoft.com.bd
License: MIT
Classifier: Framework :: Django
Classifier: Framework :: Django :: 3.2
Classifier: Programming Language :: Python :: 3
Classifier: Programming Language :: Python :: 3.6
Classifier: Programming Language :: Python :: 3.7
Classifier: Programming Language :: Python :: 3.8
Classifier: Programming Language :: Python :: 3.9
Classifier: License :: OSI Approved :: MIT License
Classifier: Operating System :: OS Independent
Classifier: Topic :: Security
Classifier: Topic :: Software Development :: Libraries :: Python Modules
Requires-Python: >=3.6
License-File: LICENSE
Requires-Dist: Django>=3.2
Requires-Dist: pyotp>=2.3.0
Requires-Dist: qrcode>=6.1
Requires-Dist: Pillow>=7.0
Dynamic: author
Dynamic: author-email
Dynamic: classifier
Dynamic: description
Dynamic: description-content-type
Dynamic: home-page
Dynamic: license
Dynamic: license-file
Dynamic: requires-dist
Dynamic: requires-python
Dynamic: summary
